sitesize/__init__.py
sitesize/core.py
test/__init__.py
test/test_url.py
sitesize-0.0.2.dist-info/LICENSE
sitesize-0.0.2.dist-info/METADATA
sitesize-0.0.2.dist-info/WHEEL
sitesize-0.0.2.dist-info/top_level.txt
sitesize-0.0.2.dist-info/RECORD
