Metadata-Version: 2.1
Name: sitesize
Version: 0.0.2
Summary: Get size of web page
Home-page: https://github.com/mianto/sitesize
Author: Siddhant Shaw
Author-email: siddhantshaw97@gmail.com
License: UNKNOWN
Platform: UNKNOWN
Classifier: Programming Language :: Python :: 3
Classifier: License :: OSI Approved :: MIT License
Classifier: Operating System :: OS Independent
